{
  "page": 1,
  "results": [
    {
      "original_name": "Watchmen",
      "id": 79788,
      "name": "Watchmen",
      "vote_count": 101,
      "vote_average": 7.5,
      "first_air_date": "2019-10-20",
      "poster_path": "/m8rWq3j73ZGhDuSCZWMMoE9ePH1.jpg",
      "genre_ids": [
        80,
        18,
        10759,
        10765
      ],
      "original_language": "en",
      "backdrop_path": "/gFeaXBnOO14aOQhMQrr5tbyhMTw.jpg",
      "overview": "Set in an alternate history where “superheroes” are treated as outlaws, “Watchmen” embraces the nostalgia of the original groundbreaking graphic novel while attempting to break new ground of its own.",
      "origin_country": [
        "US"
      ],
      "popularity": 84.022,
      "media_type": "tv"
    },
    {
      "original_name": "The Expanse",
      "id": 63639,
      "name": "The Expanse",
      "vote_count": 781,
      "vote_average": 7.6,
      "first_air_date": "2015-12-14",
      "poster_path": "/wikmaI7OVqmq2O9HfknkzxX6Ygu.jpg",
      "genre_ids": [
        18,
        9648,
        10765
      ],
      "original_language": "en",
      "backdrop_path": "/beIjmWr3OBOtcWK4tKMObOIDJ1C.jpg",
      "overview": "A thriller set two hundred years in the future following the case of a missing young woman who brings a hardened detective and a rogue ship's captain together in a race across the solar system to expose the greatest conspiracy in human history.",
      "origin_country": [
        "US"
      ],
      "popularity": 100.654,
      "media_type": "tv"
    },
    {
      "original_name": "The Mandalorian",
      "id": 82856,
      "name": "The Mandalorian",
      "vote_count": 284,
      "vote_average": 7.8,
      "first_air_date": "2019-11-12",
      "poster_path": "/BbNvKCuEF4SRzFXR16aK6ISFtR.jpg",
      "genre_ids": [
        10759,
        10765
      ],
      "original_language": "en",
      "backdrop_path": "/o7qi2v4uWQ8bZ1tW3KI0Ztn2epk.jpg",
      "overview": "Set after the fall of the Empire and before the emergence of the First Order, we follow the travails of a lone gunfighter in the outer reaches of the galaxy far from the authority of the New Republic.",
      "origin_country": [
        "US"
      ],
      "popularity": 467.548,
      "media_type": "tv"
    },
    {
      "original_name": "Rick and Morty",
      "id": 60625,
      "name": "Rick and Morty",
      "vote_count": 1581,
      "vote_average": 8.6,
      "first_air_date": "2013-12-02",
      "poster_path": "/qJdfO3ahgAMf2rcmhoqngjBBZW1.jpg",
      "genre_ids": [
        16,
        35,
        10759,
        10765
      ],
      "original_language": "en",
      "backdrop_path": "/mzzHr6g1yvZ05Mc7hNj3tUdy2bM.jpg",
      "overview": "Rick is a mentally-unbalanced but scientifically-gifted old man who has recently reconnected with his family. He spends most of his time involving his young grandson Morty in dangerous, outlandish adventures throughout space and alternate universes. Compounded with Morty's already unstable family life, these events cause Morty much distress at home and school.",
      "origin_country": [
        "US"
      ],
      "popularity": 336.088,
      "media_type": "tv"
    },
    {
      "original_name": "His Dark Materials",
      "id": 68507,
      "name": "His Dark Materials",
      "vote_count": 115,
      "vote_average": 7.6,
      "first_air_date": "2019-11-03",
      "poster_path": "/xOjRNnQw5hqR1EULJ2iHkGwJVA4.jpg",
      "genre_ids": [
        18,
        10765
      ],
      "original_language": "en",
      "backdrop_path": "/9yKCJTOh9m3Lol2RY3kw99QPH6x.jpg",
      "overview": "Lyra is an orphan who lives in a parallel universe in which science, theology and magic are entwined. Lyra's search for a kidnapped friend uncovers a sinister plot involving stolen children, and turns into a quest to understand a mysterious phenomenon called Dust. She is later joined on her journey by Will, a boy who possesses a knife that can cut windows between worlds. As Lyra learns the truth about her parents and her prophesied destiny, the two young people are caught up in a war against celestial powers that ranges across many worlds.",
      "origin_country": [
        "GB"
      ],
      "popularity": 197.843,
      "media_type": "tv"
    },
    {
      "original_name": "Game of Thrones",
      "id": 1399,
      "name": "Game of Thrones",
      "vote_count": 6556,
      "vote_average": 8.2,
      "first_air_date": "2011-04-17",
      "poster_path": "/u3bZgnGQ9T01sWNhyveQz0wH0Hl.jpg",
      "genre_ids": [
        18,
        10759,
        10765
      ],
      "original_language": "en",
      "backdrop_path": "/suopoADq0k8YZr4dQXcU6pToj6s.jpg",
      "overview": "Seven noble families fight for control of the mythical land of Westeros. Friction between the houses leads to full-scale war. All while a very ancient evil awakens in the farthest north. Amidst the war, a neglected military order of misfits, the Night's Watch, is all that stands between the realms of men and icy horrors beyond.",
      "origin_country": [
        "US"
      ],
      "popularity": 92.381,
      "media_type": "tv"
    },
    {
      "original_name": "Vikings",
      "id": 44217,
      "name": "Vikings",
      "vote_count": 1809,
      "vote_average": 7.5,
      "first_air_date": "2013-03-03",
      "poster_path": "/ff1zhqvwfS5HvRNcA5UFrH0PA2q.jpg",
      "genre_ids": [
        18,
        10759
      ],
      "original_language": "en",
      "backdrop_path": "/aq2yEMgRQBPfRkrO0Repo2qhUAT.jpg",
      "overview": "The adventures of Ragnar Lothbrok, the greatest hero of his age. The series tells the sagas of Ragnar's band of Viking brothers and his family, as he rises to become King of the Viking tribes. As well as being a fearless warrior, Ragnar embodies the Norse traditions of devotion to the gods. Legend has it that he was a direct descendant of Odin, the god of war and warriors.",
      "origin_country": [
        "CA"
      ],
      "popularity": 143.814,
      "media_type": "tv"
    },
    {
      "original_name": "Mr. Robot",
      "id": 62560,
      "name": "Mr. Robot",
      "vote_count": 1632,
      "vote_average": 7.9,
      "first_air_date": "2015-05-27",
      "poster_path": "/oKIBhzZzDX07SoE2bOLhq2EE8rf.jpg",
      "genre_ids": [
        80,
        18
      ],
      "original_language": "en",
      "backdrop_path": "/4n0TZfTUSUELqRrOA8sZKWs9bWU.jpg",
      "overview": "A contemporary and culturally resonant drama about a young programmer, Elliot, who suffers from a debilitating anti-social disorder and decides that he can only connect to people by hacking them. He wields his skills as a weapon to protect the people that he cares about. Elliot will find himself in the intersection between a cybersecurity firm he works for and the underworld organizations that are recruiting him to bring down corporate America.",
      "origin_country": [
        "US"
      ],
      "popularity": 81.802,
      "media_type": "tv"
    },
    {
      "original_name": "Marvel's Runaways",
      "id": 67466,
      "name": "Marvel's Runaways",
      "vote_count": 166,
      "vote_average": 7.7,
      "first_air_date": "2017-11-21",
      "poster_path": "/zceMrfO17AQkeWJZNra4O90s1vE.jpg",
      "genre_ids": [
        80,
        18,
        10759,
        10765
      ],
      "original_language": "en",
      "backdrop_path": "/7PYAUaJzzUVxS4xiJHFe338vJd1.jpg",
      "overview": "Every teenager thinks their parents are evil. What if you found out they actually were? Six diverse teenagers who can barely stand each other must unite against a common foe – their parents.",
      "origin_country": [
        "US"
      ],
      "popularity": 48.372,
      "media_type": "tv"
    },
    {
      "original_name": "See",
      "id": 80752,
      "name": "See",
      "vote_count": 120,
      "vote_average": 7.7,
      "first_air_date": "2019-11-01",
      "poster_path": "/g3JsScc7mQCfc3e5e5rXwu7xVVP.jpg",
      "genre_ids": [
        18,
        10759,
        10765
      ],
      "original_language": "en",
      "backdrop_path": "/8TOkxONO3TEeJRuZWb0hG7SboyV.jpg",
      "overview": "A virus has decimated humankind. Those who survived emerged blind. Centuries later when twins are born with the mythic ability to see, their father must protect his tribe against a threatened queen.",
      "origin_country": [
        "US"
      ],
      "popularity": 53.76,
      "media_type": "tv"
    },
    {
      "original_name": "Shameless",
      "id": 34307,
      "name": "Shameless",
      "vote_count": 927,
      "vote_average": 7.9,
      "first_air_date": "2011-01-09",
      "poster_path": "/m2gf7SYOq9z30Q1dJFMF51DfrmF.jpg",
      "genre_ids": [
        35,
        18
      ],
      "original_language": "en",
      "backdrop_path": "/1ccgQ6IJyEc8UHPtGeFFeRqMVnc.jpg",
      "overview": "Chicagoan Frank Gallagher is the proud single dad of six smart, industrious, independent kids, who without him would be... perhaps better off. When Frank's not at the bar spending what little money they have, he's passed out on the floor. But the kids have found ways to grow up in spite of him. They may not be like any family you know, but they make no apologies for being exactly who they are.",
      "origin_country": [
        "US"
      ],
      "popularity": 82.935,
      "media_type": "tv"
    },
    {
      "original_name": "Good Trouble",
      "id": 80006,
      "name": "Good Trouble",
      "vote_count": 30,
      "vote_average": 7.5,
      "first_air_date": "2019-01-08",
      "poster_path": "/ql1ke1VC3fG4ES9N0d2dFgaIntP.jpg",
      "genre_ids": [
        18
      ],
      "original_language": "en",
      "backdrop_path": "/hBYvHCcZX4dyvXeM0NTBh5uJIk3.jpg",
      "overview": "After moving to The Coterie in Downtown Los Angeles, Callie and Mariana Foster realize that living on their own is not all that it’s cracked up to be.",
      "origin_country": [
        "US"
      ],
      "popularity": 21.47,
      "media_type": "tv"
    },
    {
      "original_name": "사랑의 불시착",
      "id": 94796,
      "name": "Crash Landing on You",
      "vote_count": 1,
      "vote_average": 8,
      "first_air_date": "2019-12-14",
      "poster_path": "/roxAwowl4kwKC4QD2G4tDAeodSX.jpg",
      "genre_ids": [
        35,
        18
      ],
      "original_language": "ko",
      "backdrop_path": "/o3Htmlg6BfNs8Ew7yjsRzVnYSEs.jpg",
      "overview": "Yoon Se-Ri is an heiress to a conglomerate in South Korea. One day, while paragliding, an accident caused by strong winds leads Yoon Se-Ri to make an emergency landing in North Korea. There, she meets Lee Jung-Hyeok, who is a North Korean army officer. He tries to protect her and hide her. Soon, Lee Jung-Hyeok falls in love with Yoon Se-Ri.",
      "origin_country": [
        "KR"
      ],
      "popularity": 28.282,
      "media_type": "tv"
    },
    {
      "original_name": "The Simpsons",
      "id": 456,
      "name": "The Simpsons",
      "vote_count": 2270,
      "vote_average": 7.2,
      "first_air_date": "1989-12-17",
      "poster_path": "/yTZQkSsxUFJZJe67IenRM0AEklc.jpg",
      "genre_ids": [
        16,
        35
      ],
      "original_language": "en",
      "backdrop_path": "/f5uNbUC76oowt5mt5J9QlqrIYQ6.jpg",
      "overview": "Set in Springfield, the average American town, the show focuses on the antics and everyday adventures of the Simpson family; Homer, Marge, Bart, Lisa and Maggie, as well as a virtual cast of thousands. Since the beginning, the series has been a pop culture icon, attracting hundreds of celebrities to guest star. The show has also made name for itself in its fearless satirical take on politics, media and American life in general.",
      "origin_country": [
        "US"
      ],
      "popularity": 161.44,
      "media_type": "tv"
    },
    {
      "original_name": "The Voice",
      "id": 37678,
      "name": "The Voice",
      "vote_count": 90,
      "vote_average": 5.1,
      "first_air_date": "2011-04-26",
      "poster_path": "/wNOaBmA0jnd624aMrJg5JlsNz5U.jpg",
      "genre_ids": [
        10764
      ],
      "original_language": "en",
      "backdrop_path": "/1ZdpQK88egEU0enpQtJQGMUyBC9.jpg",
      "overview": "The strongest vocalists from across the United states compete in a blockbusters vocal competition, the winner becomes “The Voice.” The show's innovative format features four stages of competition: the blind auditions, the battle rounds, the knockouts and, finally, the live performance shows.",
      "origin_country": [
        "US",
        "NL"
      ],
      "popularity": 25.735,
      "media_type": "tv"
    },
    {
      "original_name": "The Flash",
      "id": 60735,
      "name": "The Flash",
      "vote_count": 3075,
      "vote_average": 6.7,
      "first_air_date": "2014-10-07",
      "poster_path": "/wHa6KOJAoNTFLFtp7wguUJKSnju.jpg",
      "genre_ids": [
        18,
        10765
      ],
      "original_language": "en",
      "backdrop_path": "/6ZdQTBy20HzWudZthAV7NkZWfIb.jpg",
      "overview": "After a particle accelerator causes a freak storm, CSI Investigator Barry Allen is struck by lightning and falls into a coma. Months later he awakens with the power of super speed, granting him the ability to move through Central City like an unseen guardian angel. Though initially excited by his newfound powers, Barry is shocked to discover he is not the only \"meta-human\" who was created in the wake of the accelerator explosion -- and not everyone is using their new powers for good. Barry partners with S.T.A.R. Labs and dedicates his life to protect the innocent. For now, only a few close friends and associates know that Barry is literally the fastest man alive, but it won't be long before the world learns what Barry Allen has become...The Flash.",
      "origin_country": [
        "US"
      ],
      "popularity": 150.97,
      "media_type": "tv"
    },
    {
      "original_name": "The Witcher",
      "id": 71912,
      "name": "The Witcher",
      "vote_count": 0,
      "vote_average": 0,
      "first_air_date": "2019-12-20",
      "poster_path": "/zrPpUlehQaBf8YX2NrVrKK8IEpf.jpg",
      "genre_ids": [
        18,
        10765
      ],
      "original_language": "en",
      "backdrop_path": "/6WIe91OEkZhmgMSL7GnX3WuPG1R.jpg",
      "overview": "The witcher Geralt, a mutated monster hunter, struggles to find his place in a world where people often prove more wicked than beasts. Based on Andrzej Sapkowski's Witcher Saga.",
      "origin_country": [
        "PL",
        "US"
      ],
      "popularity": 27.346,
      "media_type": "tv"
    },
    {
      "original_name": "Arrow",
      "id": 1412,
      "name": "Arrow",
      "vote_count": 2921,
      "vote_average": 5.8,
      "first_air_date": "2012-10-10",
      "poster_path": "/gKG5QGz5Ngf8fgWpBsWtlg5L2SF.jpg",
      "genre_ids": [
        80,
        18,
        9648,
        10759
      ],
      "original_language": "en",
      "backdrop_path": "/dXTyVDTIgeByvUOUEiHjbi8xX9A.jpg",
      "overview": "Spoiled billionaire playboy Oliver Queen is missing and presumed dead when his yacht is lost at sea. He returns five years later a changed man, determined to clean up the city as a hooded vigilante armed with a bow.",
      "origin_country": [
        "US"
      ],
      "popularity": 168.309,
      "media_type": "tv"
    },
    {
      "original_name": "The Purge",
      "id": 80213,
      "name": "The Purge",
      "vote_count": 68,
      "vote_average": 6.8,
      "first_air_date": "2018-09-04",
      "poster_path": "/9CaS2XFd0Db42grzzVBnWcSkrbg.jpg",
      "genre_ids": [
        80,
        18,
        9648
      ],
      "original_language": "en",
      "backdrop_path": "/rFGtqUOIXP9CudLaSzK9iFZB7lK.jpg",
      "overview": "Set in a dystopian America ruled by a totalitarian political party, the series follows several seemingly unrelated characters living in a small city. Tying them all together is a mysterious savior who’s impeccably equipped for everything the night throws at them. As the clock winds down with their fates hanging in the balance, each character is forced to reckon with their pasts as they discover how far they will go to survive the night.",
      "origin_country": [
        "US"
      ],
      "popularity": 19.599,
      "media_type": "tv"
    },
    {
      "original_name": "The L Word: Generation Q",
      "id": 89630,
      "name": "The L Word: Generation Q",
      "vote_count": 3,
      "vote_average": 10,
      "first_air_date": "2019-12-08",
      "poster_path": "/yJi4XF31vgIaI1J34RAOlFFo3Pv.jpg",
      "genre_ids": [
        18
      ],
      "original_language": "en",
      "backdrop_path": "/kIDmBojnkQotpnNYD62kZ6MGMia.jpg",
      "overview": "In this sequel to The L Word, we continue to follow the intermingled lives of Bette Porter, Alice Pieszecki and Shane McCutcheon, along with a new generation of diverse, self-possessed LGBTQIA+ characters experiencing love, heartbreak, sex, setbacks and success in L.A.",
      "origin_country": [
        "US"
      ],
      "popularity": 43.775,
      "media_type": "tv"
    }
  ],
  "total_pages": 1000,
  "total_results": 20000
}